__init__.py
compare_dataset_with_standard.py
compare_models.py
modal_server.py
run_model.py
train_remote.py
pflows/__init__.py
pflows/cli.py
pflows/model.py
pflows/polygons.py
pflows/try_augmentations.ipynb
pflows/typedef.py
pflows/workflow.py
pflows/tools/__init__.py
pflows/tools/annotations.py
pflows/tools/augmentations.py
pflows/tools/base.py
pflows/tools/categories.py
pflows/tools/compare_datasets.py
pflows/tools/dataset.py
pflows/tools/external.py
pflows/tools/filter_images.py
pflows/tools/images.py
pflows/tools/pflows_remote.py
pflows/tools/roboflow_tools.py
pflows/tools/yolo_v8.py
pflows/viewer/review_images.py
pflows-0.1.23.dist-info/LICENSE
pflows-0.1.23.dist-info/METADATA
pflows-0.1.23.dist-info/WHEEL
pflows-0.1.23.dist-info/entry_points.txt
pflows-0.1.23.dist-info/top_level.txt
pflows-0.1.23.dist-info/RECORD
