Metadata-Version: 2.2
Name: pflows
Version: 0.1.23
Summary: Several tools by dealing with image annotations to train YOLO or similar models
Author-email: Daniel Pérez Rada <dperezrada@gmail.com>
Maintainer-email: Daniel Pérez Rada <dperezrada@gmail.com>
License: MIT license
Project-URL: bugs, https://github.com/dperezrada/pflows/issues
Project-URL: changelog, https://github.com/dperezrada/pflows/blob/master/changelog.md
Project-URL: homepage, https://github.com/dperezrada/pflows
License-File: LICENSE
Requires-Dist: pillow==10.3.0
Requires-Dist: roboflow==1.1.28
Requires-Dist: scikit-image==0.23.2
Requires-Dist: PyYAML==6.0.1
Requires-Dist: opencv-python==4.8.0.74
Requires-Dist: opencv-python-headless==4.8.0.74
Requires-Dist: shapely==2.0.4
Requires-Dist: albumentations==1.3.1
Requires-Dist: python-dotenv==1.0.1
Requires-Dist: fastapi==0.111.0
Requires-Dist: fastapi-cli==0.0.4
Requires-Dist: modal==0.62.181
Requires-Dist: requests==2.31.0
Requires-Dist: requests-toolbelt==1.0.0
Requires-Dist: numpy==1.26.4
Requires-Dist: tabulate==0.9.0
Requires-Dist: imagesize==1.4.1
Requires-Dist: ultralytics==8.3.26
Provides-Extra: dev
Requires-Dist: pytest==6.2.4; extra == "dev"
Requires-Dist: pylint==3.1.1; extra == "dev"
Requires-Dist: mypy==1.10.0; extra == "dev"
Requires-Dist: types-PyYAML==6.0.12.20240311; extra == "dev"
Requires-Dist: black==24.4.2; extra == "dev"
Requires-Dist: pytest-cov==5.0.0; extra == "dev"
Requires-Dist: types-tabulate==0.9.0.20240106; extra == "dev"
